{
  "$schema": "https://schema.management.azure.com/schemas/2019-04-01/deploymentTemplate.json#",
  "contentVersion": "1.0.0.0",
  "parameters": {
    "virtualMachineName": {
      "type": "String",
      "defaultValue": "myVM",
      "metadata": {
        "description": "The name of the VM"
      }
    },
    "virtualMachineSize": {
      "type": "String",
      "defaultValue": "Standard_D2s_v3",
      "metadata": {
        "description": "The virtual machine size."
      }              },
     "networkInterfaceName": {
      "type": "string",
      "defaultValue": "xxx-nic01"
    },
    "virtualNetworkId": {
      "type": "String",
      "defaultValue": "/subscriptions/subscriptionid/resourceGroups/rg-prod-vnet-01/providers/Microsoft.Network/virtualNetworks/vnet-prod-01",
      "metadata": {
        "description": "Specify the name of an existing VNet in the same resource group"
      }
    },
    "existingVnetResourceGroup": {
      "type": "String",
      "defaultValue": "rg-prod-vnet-01",
      "metadata": {
        "description": "Specify the resource group of the existing VNet"
      }
    },
    "subnetName": {
      "type": "String",
      "defaultValue": "snet-prod-servers-01",
      "metadata": {
        "description": "Specify the name of the Subnet Name"
      }
    },
    "imageOffer": {
      "type": "String",
      "defaultValue": "sql2019-ws2019",
      "allowedValues": [
        "sql2019-ws2019",
        "sql2017-ws2019",
        "SQL2017-WS2016",
        "SQL2016SP1-WS2016",
        "SQL2016SP2-WS2016",
        "SQL2014SP3-WS2012R2",
        "SQL2014SP2-WS2012R2"
      ],
      "metadata": {
        "description": "Windows Server and SQL Offer"
      }
    },
    "sqlSku": {
      "type": "String",
      "defaultValue": "Standard",
      "allowedValues": [
        "Standard",
        "Enterprise",
        "SQLDEV",
        "Web",
        "Express"
      ],
      "metadata": {
        "description": "SQL Server Sku"
      }
    },
    "adminUsername": {
      "type": "String",
      "defaultValue": "servermaster",
      "metadata": {
        "description": "The admin user name of the VM"
      }
    },
    "adminPassword": {
      "type": "SecureString",
      "metadata": {
        "description": "The admin password of the VM"
      }
    },
    "storageWorkloadType": {
      "type": "String",
      "defaultValue": "General",
      "allowedValues": [
        "General",
        "OLTP",
        "DW"
      ],
      "metadata": {
        "description": "SQL Server Workload Type"
      }
    },
    "sqlDataDisksCount": {
      "type": "int",
      "defaultValue": 1,
      "minValue": 1,
      "maxValue": 8,
      "metadata": {
        "description": "Amount of data disks (128GB each) for SQL Data files"
      }
    },
    "dataPath": {
      "type": "String",
      "defaultValue": "F:\\SQLData",
      "metadata": {
        "description": "Path for SQL Data files. Please choose drive letter from F to Z, and other drives from A to E are reserved for system"
      }
    },
    "sqlLogDisksCount": {
      "type": "int",
      "defaultValue": 1,
      "minValue": 1,
      "maxValue": 8,
      "metadata": {
        "description": "Amount of data disks (128GB each) for SQL Log files"
      }
    },
    "logPath": {
      "type": "String",
      "defaultValue": "G:\\SQLLog",
      "metadata": {
        "description": "Path for SQL Log files. Please choose drive letter from F to Z and different than the one used for SQL data. Drive letter from A to E are reserved for system"
      }
    },
    "location": {
      "type": "string",
      "defaultValue": "[resourceGroup().location]",
      "metadata": {
        "description": "Location for all resources."
      }
    }
  },
  "variables": {
    "diskConfigurationType": "NEW",
     "vnetId": "[parameters('virtualNetworkId')]",
    "subnetRef": "[concat(variables('vnetId'), '/subnets/', parameters('subnetName'))]",
    "dataDisksLuns": "[array(range(0 ,parameters('sqlDataDisksCount')))]",
    "logDisksLuns": "[array(range(parameters('sqlDataDisksCount'), parameters('sqlLogDisksCount')))]",
    "dataDisks": {
      "createOption": "empty",
      "caching": "ReadOnly",
      "writeAcceleratorEnabled": false,
      "storageAccountType": "Premium_LRS",
      "diskSizeGB": 128
    },
    "tempDbPath": "D:\\SQLTemp"
  },
  "resources": [
    {
      "type": "Microsoft.Network/networkInterfaces",
      "apiVersion": "2020-06-01",
      "name": "[parameters('networkInterfaceName')]",
      "location": "[parameters('location')]",
      "properties": {
        "ipConfigurations": [
          {
            "name": "ipconfig1",
            "properties": {
              "subnet": {
                "id": "[variables('subnetRef')]"
              },
              "privateIPAllocationMethod": "Dynamic"
            }
          }
        ],
        "enableAcceleratedNetworking": false
      }
    },
    {
      "type": "Microsoft.Compute/virtualMachines",
      "apiVersion": "2020-06-01",
      "name": "[parameters('virtualMachineName')]",
      "location": "[parameters('location')]",
      "dependsOn": [
        "[resourceId('Microsoft.Network/networkInterfaces/', parameters('networkInterfaceName'))]"
      ],
      "properties": {
        "hardwareProfile": {
          "vmSize": "[parameters('virtualMachineSize')]"
        },
        "storageProfile": {
          "osDisk": {
            "name": "[concat(parameters('virtualMachineName'), '-osdisk')]",
            "createOption": "fromImage",
            "managedDisk": {
              "storageAccountType": "Premium_LRS"
            }
          },
          "imageReference": {
            "publisher": "MicrosoftSQLServer",
            "offer": "[parameters('imageOffer')]",
            "sku": "[parameters('sqlSku')]",
            "version": "latest"
          },
          "copy": [
            {
              "name": "datadisks",
              "count": "[add(parameters('sqlDataDisksCount'), parameters('sqlLogDisksCount'))]",
              "input": {   
                "name": "[concat(parameters('virtualMachineName'), '-dataDisk', padLeft(copyIndex('dataDisks'), 2, '0'))]",             
                "lun": "[copyIndex('dataDisks')]",
                "createOption": "[variables('dataDisks').createOption]",
                "caching": "[if(greaterOrEquals(copyIndex('dataDisks'), parameters('sqlDataDisksCount')) ,'None', variables('dataDisks').caching )]",
                "writeAcceleratorEnabled": "[variables('dataDisks').writeAcceleratorEnabled]",
                "diskSizeGB": "[variables('dataDisks').diskSizeGB]",
                "managedDisk": {
                  "storageAccountType": "[variables('dataDisks').storageAccountType]"
                }
              }
            }
          ]
        },
        "networkProfile": {
          "networkInterfaces": [
            {
              "id": "[resourceId('Microsoft.Network/networkInterfaces', parameters('networkInterfaceName'))]"
            }
          ]
        },
        "osProfile": {
          "computerName": "[parameters('virtualMachineName')]",
          "adminUsername": "[parameters('adminUsername')]",
          "adminPassword": "[parameters('adminPassword')]",
          "windowsConfiguration": {
            "enableAutomaticUpdates": false,
            "provisionVmAgent": true
          }
        }
      }
    },
    {
      "type": "Microsoft.SqlVirtualMachine/SqlVirtualMachines",
      "apiVersion": "2017-03-01-preview",
      "name": "[parameters('virtualMachineName')]",
      "location": "[parameters('location')]",
      "dependsOn": [
        "[resourceId('Microsoft.Compute/virtualMachines', parameters('virtualMachineName'))]"
      ],
      "properties": {
        "virtualMachineResourceId": "[resourceId('Microsoft.Compute/virtualMachines', parameters('virtualMachineName'))]",
        "sqlManagement": "Full",
        "SqlServerLicenseType": "PAYG",
        "StorageConfigurationSettings": {
          "DiskConfigurationType": "[variables('diskConfigurationType')]",
          "StorageWorkloadType": "[parameters('storageWorkloadType')]",
          "SQLDataSettings": {
            "LUNs": "[variables('dataDisksLUNs')]",
            "DefaultFilePath": "[parameters('dataPath')]"
          },
          "SQLLogSettings": {
            "Luns": "[variables('logDisksLUNs')]",
            "DefaultFilePath": "[parameters('logPath')]"
          },
          "SQLTempDbSettings": {
            "DefaultFilePath": "[variables('tempDbPath')]"
          }
        }
      }
    }
  ],
  "outputs": {
    "adminUsername": {
      "type": "String",
      "value": "[parameters('adminUsername')]"
    }
  }
}
